{"157":{"country":"Australia","continent":"Oceania","code":"AU"},"158":{"country":"Australia","continent":"Oceania","code":"AU"},"159":{"country":"Australia","continent":"Oceania","code":"AU"},"163":{"country":"New Zealand","continent":"Oceania","code":"NZ"},"164":{"country":"New Zealand","continent":"Oceania","code":"NZ"},"165":{"country":"New Zealand","continent":"Oceania","code":"NZ"},"-72":{"country":"Chile","continent":"South America","code":"CL"},"-71":{"country":"Chile","continent":"South America","code":"CL"},"-70":{"country":"Chile","continent":"South America","code":"CL"},"-69":{"country":"Chile","continent":"South America","code":"CL"},"-68":{"country":"Chile","continent":"South America","code":"CL"},"-67":{"country":"Chile","continent":"South America","code":"CL"},"-66":{"country":"Argentina","continent":"South America","code":"AR"},"-65":{"country":"Argentina","continent":"South America","code":"AR"},"-64":{"country":"Argentina","continent":"South America","code":"AR"},"-47":{"country":"United Kingdom","continent":"Europe","code":"GB"},"-46":{"country":"United Kingdom","continent":"Europe","code":"GB"},"-45":{"country":"United Kingdom","continent":"Europe","code":"GB"},"-44":{"country":"United Kingdom","continent":"Europe","code":"GB"},"-43":{"country":"United Kingdom","continent":"Europe","code":"GB"},"-42":{"country":"United Kingdom","continent":"Europe","code":"GB"},"-41":{"country":"United Kingdom","continent":"Europe","code":"GB"},"-40":{"country":"United Kingdom","continent":"Europe","code":"GB"},"-39":{"country":"United Kingdom","continent":"Europe","code":"GB"},"-38":{"country":"United Kingdom","continent":"Europe","code":"GB"},"-37":{"country":"United Kingdom","continent":"Europe","code":"GB"},"-36":{"country":"United Kingdom","continent":"Europe","code":"GB"},"-35":{"country":"United Kingdom","continent":"Europe","code":"GB"},"-34":{"country":"United Kingdom","continent":"Europe","code":"GB"},"-33":{"country":"United Kingdom","continent":"Europe","code":"GB"},"-32":{"country":"United Kingdom","continent":"Europe","code":"GB"},"-31":{"country":"United Kingdom","continent":"Europe","code":"GB"},"-30":{"country":"United Kingdom","continent":"Europe","code":"GB"},"-29":{"country":"United Kingdom","continent":"Europe","code":"GB"},"-28":{"country":"United Kingdom","continent":"Europe","code":"GB"},"-27":{"country":"United Kingdom","continent":"Europe","code":"GB"}}